[
 {
   "Offerid": 1,
   "OfferDetails": "A1",
   "OfferImgURL": "A1.jpg",
   "OfferStartDate": "30-05-2018",
   "OfferEndDate": "31-05-2018"
 },
 {
   "Offerid": 2,
   "OfferDetails": "A2",
   "OfferImgURL": "A2.jpg",
   "OfferStartDate": "31-05-2018",
   "OfferEndDate": "01-06-2018"
 },
 {
   "Offerid": 3,
   "OfferDetails": "A3",
   "OfferImgURL": "A3.jpg",
   "OfferStartDate": "01-06-2018",
   "OfferEndDate": "02-06-2018"
 },
 {
   "Offerid": 4,
   "OfferDetails": "A4",
   "OfferImgURL": "A4.jpg",
   "OfferStartDate": "02-06-2018",
   "OfferEndDate": "03-06-2018"
 },
 {
   "Offerid": 5,
   "OfferDetails": "A5",
   "OfferImgURL": "A5.jpg",
   "OfferStartDate": "03-06-2018",
   "OfferEndDate": "04-06-2018"
 },
 {
   "Offerid": 6,
   "OfferDetails": "A6",
   "OfferImgURL": "A6.jpg",
   "OfferStartDate": "04-06-2018",
   "OfferEndDate": "05-06-2018"
 },
 {
   "Offerid": 7,
   "OfferDetails": "A7",
   "OfferImgURL": "A7.jpg",
   "OfferStartDate": "05-06-2018",
   "OfferEndDate": "06-06-2018"
 },
 {
   "Offerid": 8,
   "OfferDetails": "A8",
   "OfferImgURL": "A8.jpg",
   "OfferStartDate": "06-06-2018",
   "OfferEndDate": "07-06-2018"
 },
 {
   "Offerid": 9,
   "OfferDetails": "A9",
   "OfferImgURL": "A9.jpg",
   "OfferStartDate": "07-06-2018",
   "OfferEndDate": "08-06-2018"
 },
 {
   "Offerid": 10,
   "OfferDetails": "A10",
   "OfferImgURL": "A10.jpg",
   "OfferStartDate": "08-06-2018",
   "OfferEndDate": "09-06-2018"
 },
 {
   "Offerid": 11,
   "OfferDetails": "A11",
   "OfferImgURL": "A11.jpg",
   "OfferStartDate": "09-06-2018",
   "OfferEndDate": "10-06-2018"
 }
]